aikit/__init__.py
aikit/__meta__.py
aikit/cross_validation.py
aikit/enums.py
aikit/logging.py
aikit/model_definition.py
aikit/model_registration.py
aikit/pipeline.py
aikit/plot.py
aikit/scorer.py
aikit/datasets/__init__.py
aikit/datasets/datasets.py
aikit/ml_machine/__init__.py
aikit/ml_machine/data_persister.py
aikit/ml_machine/default.py
aikit/ml_machine/hyper_parameters.py
aikit/ml_machine/jobs.py
aikit/ml_machine/ml_machine.py
aikit/ml_machine/ml_machine_guider.py
aikit/ml_machine/ml_machine_launcher.py
aikit/ml_machine/ml_machine_registration.py
aikit/ml_machine/model_graph.py
aikit/ml_machine/model_registrer.py
aikit/ml_machine/steps_handling.py
aikit/models/__init__.py
aikit/models/base.py
aikit/models/ordinal.py
aikit/models/random_forest_addins.py
aikit/models/rotation_forest.py
aikit/models/sklearn_lightgbm_wrapper.py
aikit/models/stacking.py
aikit/tools/__init__.py
aikit/tools/data_structure_helper.py
aikit/tools/db_informations.py
aikit/tools/graph_helper.py
aikit/tools/helper_functions.py
aikit/tools/json_helper.py
aikit/transformers/__init__.py
aikit/transformers/base.py
aikit/transformers/block_selector.py
aikit/transformers/categories.py
aikit/transformers/model_wrapper.py
aikit/transformers/target.py
aikit/transformers/text.py
aikit-0.2.2.dist-info/LICENSE
aikit-0.2.2.dist-info/METADATA
aikit-0.2.2.dist-info/WHEEL
aikit-0.2.2.dist-info/top_level.txt
aikit-0.2.2.dist-info/RECORD
