Metadata-Version: 2.1
Name: aikit
Version: 0.2.2
Summary: An automated machine learning framework
Home-page: https://github.com/societe-generale/aikit
Maintainer: Lionel Massoulard
Maintainer-email: 
License: BSD License
Download-URL: https://pypi.org/project/aikit/#files
Platform: UNKNOWN
Classifier: Development Status :: 4 - Beta
Classifier: Intended Audience :: Science/Research
Classifier: Intended Audience :: Developers
Classifier: License :: OSI Approved :: BSD License
Classifier: Operating System :: Microsoft :: Windows
Classifier: Operating System :: POSIX
Classifier: Operating System :: Unix
Classifier: Operating System :: MacOS
Classifier: Topic :: Software Development
Classifier: Topic :: Scientific/Engineering
Classifier: Programming Language :: Python
Classifier: Programming Language :: Python :: 3
Classifier: Programming Language :: Python :: 3.4
Classifier: Programming Language :: Python :: 3.5
Classifier: Programming Language :: Python :: 3.6
Requires-Dist: scikit-learn (>=0.20)
Requires-Dist: pandas (>=0.23)
Requires-Dist: numpy
Requires-Dist: scipy
Requires-Dist: statsmodels
Requires-Dist: lockfile
Requires-Dist: decorator
Requires-Dist: networkx
